[
    {
        "club_page": "https://sop.utoronto.ca/group/dewey-fan-club/",
        "instagram_links": null,
        "instagram_usernames": null
    },
    {
        "club_page": "https://sop.utoronto.ca/group/testgroup/",
        "instagram_links": null,
        "instagram_usernames": null
    },
    {
        "club_page": "https://sop.utoronto.ca/group/the-back-end-test-group/",
        "instagram_links": null,
        "instagram_usernames": null
    },
    {
        "club_page": "https://sop.utoronto.ca/group/zzzjh-sop-test-group-1/",
        "instagram_links": null,
        "instagram_usernames": null
    },
    {
        "club_page": "https://sop.utoronto.ca/group/zoe-students/",
        "instagram_links": null,
        "instagram_usernames": null
    },
    {
        "club_page": "https://sop.utoronto.ca/group/yun/",
        "instagram_links": null,
        "instagram_usernames": null
    },
    {
        "club_page": "https://sop.utoronto.ca/group/youth-with-a-mission-go/",
        "instagram_links": null,
        "instagram_usernames": null
    }
]